LICENSE
README.md
setup.py
src/openelo/__init__.py
src/openelo/skill_adjuster.py
src/openelo/team_balancer.py
src/openelo.egg-info/PKG-INFO
src/openelo.egg-info/SOURCES.txt
src/openelo.egg-info/dependency_links.txt
src/openelo.egg-info/requires.txt
src/openelo.egg-info/top_level.txt
src/openelo/common/__init__.py
src/openelo/common/aggregation.py
src/openelo/common/bucket.py
src/openelo/common/common.py
src/openelo/common/constants.py
src/openelo/common/numericals.py
src/openelo/common/ordering.py
src/openelo/common/player.py
src/openelo/common/rating_system.py
src/openelo/common/statistics.py
src/openelo/common/team_rating_system.py
src/openelo/common/term.py
src/openelo/systems/__init__.py
src/openelo/systems/bradley_terry.py
src/openelo/systems/codeforce.py
src/openelo/systems/elo.py
src/openelo/systems/elommr.py
src/openelo/systems/endureelo.py
src/openelo/systems/glicko.py
src/openelo/systems/plackett_luce.py
src/openelo/systems/thurstone_mosteller.py
src/openelo/systems/topcoder.py
src/openelo/systems/trueskill.py