Metadata-Version: 2.1
Name: openelo
Version: 0.0.2.post2
Summary: A set of elo systems written in Python.
Home-page: https://github.com/BeniaminC/Open-ELO
Author: Beniamin Condrea
Author-email: benjamin.condrea@gmail.com
Keywords: elo,rating system,mmr,competition
Classifier: Programming Language :: Python :: 3
Classifier: License :: OSI Approved :: MIT License
Classifier: Operating System :: OS Independent
Requires-Python: >=3.12
License-File: LICENSE
Requires-Dist: numpy
Requires-Dist: scipy
Requires-Dist: nptyping
Requires-Dist: trueskill
